rm_onelineai/__init__.py
rm_onelineai/claude_module.py
rm_onelineai/gemini_module.py
rm_onelineai/openai_module.py
rm_onelineai-0.1.1.dist-info/LICENSE.txt
rm_onelineai-0.1.1.dist-info/METADATA
rm_onelineai-0.1.1.dist-info/WHEEL
rm_onelineai-0.1.1.dist-info/top_level.txt
rm_onelineai-0.1.1.dist-info/RECORD
