Metadata-Version: 2.1
Name: rm_onelineai
Version: 0.1.1
Summary: A Python module for interacting with various AI models
Home-page: https://github.com/yourusername/rm_onelineai
Author: Rohit Mane
Author-email: rohitmane2001@gmail.com
Classifier: Programming Language :: Python :: 3
Classifier: License :: OSI Approved :: MIT License
Classifier: Operating System :: OS Independent
Requires-Python: >=3.8
License-File: LICENSE.txt
Requires-Dist: openai
Requires-Dist: google-generativeai
Requires-Dist: anthropic
